README.md
setup.py
django_openehr/__init__.py
django_openehr/urls.py
django_openehr/views.py
django_openehr.egg-info/PKG-INFO
django_openehr.egg-info/SOURCES.txt
django_openehr.egg-info/dependency_links.txt
django_openehr.egg-info/not-zip-safe
django_openehr.egg-info/top_level.txt
django_openehr/migrations/0001_initial.py
django_openehr/migrations/0002_auto_20180130_2032.py
django_openehr/migrations/0003_auto_20180130_2157.py
django_openehr/migrations/0004_auto_20180131_0758.py
django_openehr/migrations/0005_auto_20180205_1757.py
django_openehr/migrations/0006_auto_20180212_1507.py
django_openehr/migrations/__init__.py
django_openehr/models/__init__.py
django_openehr/models/address_details.py
django_openehr/models/adverse_reaction.py
django_openehr/models/clinical_synopsis.py
django_openehr/models/demographic_personal.py
django_openehr/models/demographic_professional.py
django_openehr/models/identifier.py
django_openehr/models/inpatient_admission.py
django_openehr/models/person_name.py
django_openehr/models/problem_diagnosis.py
django_openehr/models/reason_for_encounter.py
django_openehr/models/relevant_contact.py
django_openehr/models/symptom_sign.py
django_openehr/models/telecom_details.py
django_openehr/models/therapeutic_direction.py