Metadata-Version: 1.0
Name: django-openehr
Version: 0.0.4
Summary: openEHR archetypes rendered as Django models
Home-page: https://github.com/openhealthcare/django_openehr
Author: Open Health Care UK
Author-email: UNKNOWN
License: MIT
Platform: UNKNOWN
